unfold_extra/.envrc
unfold_extra/__init__.py
unfold_extra/apps.py
unfold_extra/contrib/__init__.py
unfold_extra/contrib/auth/__init__.py
unfold_extra/contrib/auth/admin.py
unfold_extra/contrib/auth/apps.py
unfold_extra/contrib/cms/__init__.py
unfold_extra/contrib/cms/admin.py
unfold_extra/contrib/cms/apps.py
unfold_extra/contrib/cms/forms.py
unfold_extra/contrib/cms/utils.py
unfold_extra/contrib/cms/widgets.py
unfold_extra/contrib/cms/templates/admin/cms/page/change_form.html
unfold_extra/contrib/cms/templates/admin/cms/page/plugin/change_form.html
unfold_extra/contrib/cms/templates/djangocms_versioning/admin/grouper_form.html
unfold_extra/contrib/cms/templates/unfold_extra/cms/page/change_form.html
unfold_extra/contrib/cms/templates/unfold_extra/cms/page/tree/base.html
unfold_extra/contrib/parler/__init__.py
unfold_extra/contrib/parler/admin.py
unfold_extra/contrib/parler/apps.py
unfold_extra/contrib/parler/forms.py
unfold_extra/contrib/sites/__init__.py
unfold_extra/contrib/sites/admin.py
unfold_extra/contrib/sites/apps.py
unfold_extra/src/.nvmrc
unfold_extra/src/package.json
unfold_extra/src/vite.config.ts
unfold_extra/src/css/styles.css
unfold_extra/src/css/unfold_extra.css
unfold_extra/src/js/theme-sync.js
unfold_extra/src/js/utils/theme-utils.js
unfold_extra/static/unfold_extra/cms/css/cms.pagetree.css
unfold_extra/static/unfold_extra/cms/fonts/django-cms-iconfont.eot
unfold_extra/static/unfold_extra/cms/fonts/django-cms-iconfont.svg
unfold_extra/static/unfold_extra/cms/fonts/django-cms-iconfont.ttf
unfold_extra/static/unfold_extra/cms/fonts/django-cms-iconfont.woff
unfold_extra/static/unfold_extra/cms/fonts/django-cms-iconfont.woff2
unfold_extra/static/unfold_extra/cms/img/pagetree/tree-li-drag.gif
unfold_extra/static/unfold_extra/css/styles.css
unfold_extra/static/unfold_extra/js/theme-sync.js
unfold_extra/templatetags/__init__.py
unfold_extra/templatetags/unfold_extra_tags.py
django_unfold_extra-0.1.11.dist-info/METADATA
django_unfold_extra-0.1.11.dist-info/WHEEL
django_unfold_extra-0.1.11.dist-info/RECORD
