Metadata-Version: 2.4
Name: django-unfold-extra
Version: 0.1.11
Summary: Unofficial extra for Django Unfold Admin. Supports django-parler and django-cms.
Project-URL: Homepage, https://github.com/metaforx/django-unfold-extra
Author-email: Marc Widmer <marc@koga.cx>
License-Expression: MIT
Keywords: admin,django,django cms,tailwind,theme,unfold
Classifier: Environment :: Web Environment
Classifier: Framework :: Django
Classifier: Intended Audience :: Developers
Classifier: Operating System :: OS Independent
Classifier: Programming Language :: Python
Classifier: Programming Language :: Python :: 3.9
Classifier: Programming Language :: Python :: 3.10
Classifier: Programming Language :: Python :: 3.11
Classifier: Programming Language :: Python :: 3.12
Classifier: Programming Language :: Python :: 3.13
Requires-Python: >=3.9
Requires-Dist: django-cms>=5.0.0a1
Requires-Dist: django-parler~=2.3
Requires-Dist: django-unfold
